TheAcademyAI.py
TheAcademyAI-2.0.0.dist-info/METADATA
TheAcademyAI-2.0.0.dist-info/WHEEL
TheAcademyAI-2.0.0.dist-info/top_level.txt
TheAcademyAI-2.0.0.dist-info/RECORD
