Metadata-Version: 2.1
Name: TheAcademyAI
Version: 2.0.0
Summary: The Academy AI for beginners course
